odoo/addons/beesdoo_website_shift_swap/README.rst
odoo/addons/beesdoo_website_shift_swap/__init__.py
odoo/addons/beesdoo_website_shift_swap/__manifest__.py
odoo/addons/beesdoo_website_shift_swap/controllers/__init__.py
odoo/addons/beesdoo_website_shift_swap/controllers/controllers.py
odoo/addons/beesdoo_website_shift_swap/data/system_parameter.xml
odoo/addons/beesdoo_website_shift_swap/i18n/beesdoo_website_shift_swap.pot
odoo/addons/beesdoo_website_shift_swap/i18n/fr_BE.po
odoo/addons/beesdoo_website_shift_swap/i18n/nl_BE.po
odoo/addons/beesdoo_website_shift_swap/models/__init__.py
odoo/addons/beesdoo_website_shift_swap/models/res_config_settings.py
odoo/addons/beesdoo_website_shift_swap/readme/CONTRIBUTORS.rst
odoo/addons/beesdoo_website_shift_swap/readme/DESCRIPTION.rst
odoo/addons/beesdoo_website_shift_swap/static/description/index.html
odoo/addons/beesdoo_website_shift_swap/static/src/js/script.js
odoo/addons/beesdoo_website_shift_swap/views/assets.xml
odoo/addons/beesdoo_website_shift_swap/views/exchange_templates.xml
odoo/addons/beesdoo_website_shift_swap/views/general_templates.xml
odoo/addons/beesdoo_website_shift_swap/views/res_config_settings_view.xml
odoo/addons/beesdoo_website_shift_swap/views/solidarity_templates.xml
odoo/addons/beesdoo_website_shift_swap/views/swap_templates.xml
odoo12_addon_beesdoo_website_shift_swap-12.0.2.1.0.dist-info/METADATA
odoo12_addon_beesdoo_website_shift_swap-12.0.2.1.0.dist-info/WHEEL
odoo12_addon_beesdoo_website_shift_swap-12.0.2.1.0.dist-info/top_level.txt
odoo12_addon_beesdoo_website_shift_swap-12.0.2.1.0.dist-info/RECORD
