Metadata-Version: 2.1
Name: odoo12-addon-beesdoo-website-shift-swap
Version: 12.0.2.1.0
Summary: Add shift exchanges and solidarity shifts offers and requests.
Home-page: https://github.com/beescoop/Obeesdoo
Author: Coop IT Easy SC
License: AGPL-3
Platform: UNKNOWN
Classifier: Programming Language :: Python
Classifier: Framework :: Odoo
Classifier: Framework :: Odoo :: 12.0
Classifier: License :: OSI Approved :: GNU Affero General Public License v3
Requires-Python: >=3.5
Requires-Dist: odoo12-addon-beesdoo-shift-swap
Requires-Dist: odoo12-addon-beesdoo-website-shift
Requires-Dist: odoo (<12.1dev,>=12.0a)
